tally_cli/__init__.py
tally_cli/__main__.py
tally_cli/main.py
tally_cli/bin/tally-windows-arm64/tally.exe
tally_cli-0.2.0.dist-info/METADATA
tally_cli-0.2.0.dist-info/WHEEL
tally_cli-0.2.0.dist-info/entry_points.txt
tally_cli-0.2.0.dist-info/licenses/LICENSE
tally_cli-0.2.0.dist-info/licenses/NOTICE
tally_cli-0.2.0.dist-info/RECORD
