Metadata-Version: 2.4
Name: tally-cli
Version: 0.2.0
Summary: A fast, configurable linter for Dockerfiles and Containerfiles
Project-URL: Homepage, https://github.com/tinovyatkin/tally
Author-email: Konstantin Vyatkin <tino@vtkn.io>
License-Expression: Apache-2.0
License-File: LICENSE
License-File: NOTICE
Classifier: Environment :: Console
Classifier: Intended Audience :: Developers
Classifier: License :: OSI Approved :: Apache Software License
Classifier: Operating System :: OS Independent
Classifier: Topic :: Software Development :: Quality Assurance
Requires-Python: >=3.9
